MANIFEST.in
README.md
setup.py
PyDidYouMean.egg-info/PKG-INFO
PyDidYouMean.egg-info/SOURCES.txt
PyDidYouMean.egg-info/dependency_links.txt
PyDidYouMean.egg-info/top_level.txt
docs/Makefile
docs/conf.py
docs/index.rst
docs/make.bat
pydidyoumean/__init__.py
tests/basicTests.py