Metadata-Version: 1.1
Name: PyDidYouMean
Version: 0.1.1
Summary: A module to improve "file/command not found" error messages with "did you mean" suggestions.
Home-page: https://github.com/asweigart/pydidyoumean
Author: Al Sweigart
Author-email: al@inventwithpython.com
License: BSD
Keywords: didyoumean did you mean suggestions suggest levenshtein
Platform: UNKNOWN
Classifier: Development Status :: 4 - Beta
Classifier: Environment :: Win32 (MS Windows)
Classifier: Environment :: X11 Applications
Classifier: Environment :: MacOS X
Classifier: Intended Audience :: Developers
Classifier: License :: OSI Approved :: BSD License
Classifier: Operating System :: OS Independent
Classifier: Programming Language :: Python
Classifier: Programming Language :: Python :: 2
Classifier: Programming Language :: Python :: 2.5
Classifier: Programming Language :: Python :: 2.6
Classifier: Programming Language :: Python :: 2.7
Classifier: Programming Language :: Python :: 3
Classifier: Programming Language :: Python :: 3.1
Classifier: Programming Language :: Python :: 3.2
Classifier: Programming Language :: Python :: 3.3
Classifier: Programming Language :: Python :: 3.4
